lux_noctis/goe.py
lux_noctis/lux_qc.py
lux_noctis-0.1.0.dist-info/licenses/LICENSE
lux_noctis-0.1.0.dist-info/METADATA
lux_noctis-0.1.0.dist-info/WHEEL
lux_noctis-0.1.0.dist-info/top_level.txt
lux_noctis-0.1.0.dist-info/RECORD
