Metadata-Version: 2.4
Name: lux_noctis
Version: 0.1.0
Summary: App description
Author-email: Pedrioli Patrick <pedrioli@gmail.com>
License: LICENSE
License-File: LICENSE
Requires-Dist: matplotlib
Requires-Dist: numpy
Requires-Dist: pandas
Requires-Dist: plotly
Requires-Dist: seaborn
Requires-Dist: dousatsu
Requires-Dist: rpy2<=3.5.17
Requires-Dist: scipy
Requires-Dist: scikit-learn
Requires-Dist: upsetplot
Requires-Dist: requests
Requires-Dist: dousatsu
Requires-Dist: pyteomics[Unimod]
Requires-Dist: biopython
Requires-Dist: goatools
Provides-Extra: dev
Requires-Dist: pre-commit; extra == "dev"
Requires-Dist: build; extra == "dev"
Requires-Dist: twine; extra == "dev"
Requires-Dist: deptry; extra == "dev"
Requires-Dist: tox; extra == "dev"
Dynamic: license-file
